{"cameraMode":{"drawMode":0,"name":"Shaded","section":"Shading Mode"},"sceneLighting":true,"audioPlay":false,"sceneViewState":{"showFog":true,"showMaterialUpdate":false,"showSkybox":true,"showFlares":true,"showImageEffects":true,"showParticleSystems":true},"in2DMode":false,"pivot":{"x":7.883606910705566,"y":-8.530291557312012,"z":-20.646835327148439},"rotation":{"x":-0.09584397822618485,"y":-0.018178073689341546,"z":0.001755370874889195,"w":-0.9952993392944336},"size":667.362548828125,"orthographic":false}